drf_simple_api_signing-1.0.2.dist-info/METADATA
drf_simple_api_signing-1.0.2.dist-info/RECORD
drf_simple_api_signing-1.0.2.dist-info/WHEEL
drf_simple_api_signing-1.0.2.dist-info/top_level.txt
simple_api_signing/__init__.py
simple_api_signing/exceptions.py
simple_api_signing/utils.py
simple_api_signing/common/__init__.py
simple_api_signing/common/middleware.py
simple_api_signing/common/rest_permission.py
tests/__init__.py
tests/settings.py
tests/test_drf_permission.py
tests/test_signing_flow.py
