Metadata-Version: 2.1
Name: drf-simple-api-signing
Version: 1.0.2
Summary: A simple Django package to facilitate request signing.
Home-page: UNKNOWN
Author: Ahmed Hosny Ibrahim
Author-email: me@ahmedhosnycs.com
License: GNU GENERAL PUBLIC LICENSE
Keywords: api_signing,simple_api_signing,django
Platform: UNKNOWN
Classifier: Environment :: Web Environment
Classifier: Framework :: Django
Classifier: Framework :: Django :: 2.0
Classifier: Intended Audience :: Developers
Classifier: License :: OSI Approved :: GNU General Public License v3 or later (GPLv3+)
Classifier: Operating System :: OS Independent
Classifier: Programming Language :: Python
Classifier: Programming Language :: Python :: 3.5
Classifier: Programming Language :: Python :: 3.6
Classifier: Topic :: Internet
Classifier: Topic :: Security
Classifier: Topic :: Internet :: WWW/HTTP
Classifier: Topic :: Internet :: WWW/HTTP :: WSGI :: Application
Requires-Dist: django (>=1.10.0)
Requires-Dist: djangorestframework (>=3.0.0)
